Metadata-Version: 2.1
Name: ote
Version: 0.0.4
Summary: CLI application to generate emails and fetch OTPs
Home-page: https://github.com/s0md3v/ote
Download-URL: https://github.com/s0md3v/ote/releases
Author: Somdev Sangwan
Author-email: s0md3v@gmail.com
Maintainer: Somdev Sangwan
Maintainer-email: s0md3v@gmail.com
License: GNU General Public License v3 or later (GPLv3+)
Keywords: otp,email
Platform: any
Classifier: Development Status :: 4 - Beta
Classifier: Intended Audience :: End Users/Desktop
Classifier: Intended Audience :: Developers
Classifier: License :: OSI Approved :: GNU General Public License v3 or later (GPLv3+)
Classifier: Operating System :: OS Independent
Classifier: Programming Language :: Python :: 3.5
Classifier: Programming Language :: Python :: 3.6
Classifier: Programming Language :: Python :: 3.7
Classifier: Topic :: Utilities
License-File: LICENSE
